vina-1.2.7.dist-info/LICENSE
vina-1.2.7.dist-info/WHEEL
vina-1.2.7.dist-info/METADATA
vina-1.2.7.dist-info/top_level.txt
vina-1.2.7.dist-info/RECORD
vina.libs/libboost_atomic-34eda58a.so.1.82.0
vina.libs/libboost_program_options-401243ad.so.1.82.0
vina.libs/libboost_thread-2213d6b9.so.1.82.0
vina.libs/libboost_filesystem-f4168529.so.1.82.0
vina.libs/libboost_serialization-f02a3006.so.1.82.0
vina/__init__.py
vina/_vina_wrapper.cpython-312-x86_64-linux-gnu.so
vina/version.py
vina/vina_wrapper.py
vina/utils.py
vina/vina.py
