Metadata-Version: 2.1
Name: vina
Version: 1.2.7
Summary: Python interface to AutoDock Vina
Home-page: https://ccsb.scripps.edu/
Author: Diogo Santos Martins, Jerome Eberhardt, Andreas F. Tillack, Stefano Forli
Author-email: forli@scripps.edu
License: Apache-2.0
Classifier: Environment :: Console
Classifier: Environment :: Other Environment
Classifier: Intended Audience :: Education
Classifier: Intended Audience :: Science/Research
Classifier: License :: OSI Approved :: Apache Software License
Classifier: Natural Language :: English
Classifier: Operating System :: MacOS :: MacOS X
Classifier: Operating System :: OS Independent
Classifier: Operating System :: POSIX :: Linux
Classifier: Programming Language :: C++
Classifier: Programming Language :: Python :: 3.5
Classifier: Programming Language :: Python :: 3.6
Classifier: Programming Language :: Python :: 3.7
Classifier: Programming Language :: Python :: 3.8
Classifier: Programming Language :: Python :: 3.9
Classifier: Topic :: Scientific/Engineering :: Bio-Informatics
Classifier: Topic :: Scientific/Engineering :: Chemistry
Classifier: Topic :: Software Development :: Libraries
Requires-Python: >=3.5
License-File: LICENSE
Requires-Dist: numpy>=1.18
Requires-Dist: setuptools>=50.3
Requires-Dist: wheel
Requires-Dist: packaging
